{
    "get": "players/squads",
    "parameters": {
        "team": "46"
    },
    "errors": [],
    "results": 1,
    "paging": {
        "current": 1,
        "total": 1
    },
    "response": [
        {
            "team": {
                "id": 46,
                "name": "Leicester",
                "logo": "https://media.api-sports.io/football/teams/46.png"
            },
            "players": [
                {
                    "id": 18146,
                    "name": "D. Ward",
                    "age": 29,
                    "number": 1,
                    "position": "Goalkeeper",
                    "photo": "https://media.api-sports.io/football/players/18146.png"
                },
                {
                    "id": 18985,
                    "name": "A. Smithies",
                    "age": 32,
                    "number": 12,
                    "position": "Goalkeeper",
                    "photo": "https://media.api-sports.io/football/players/18985.png"
                },
                {
                    "id": 17736,
                    "name": "D. Iversen",
                    "age": 25,
                    "number": 31,
                    "position": "Goalkeeper",
                    "photo": "https://media.api-sports.io/football/players/17736.png"
                },
                {
                    "id": 19760,
                    "name": "J. Justin",
                    "age": 24,
                    "number": 2,
                    "position": "Defender",
                    "photo": "https://media.api-sports.io/football/players/19760.png"
                },
                {
                    "id": 8694,
                    "name": "W. Faes",
                    "age": 24,
                    "number": 3,
                    "position": "Defender",
                    "photo": "https://media-1.api-sports.io/football/players/8694.png"
                },
                {
                    "id": 18776,
                    "name": "Ç. Söyüncü",
                    "age": 26,
                    "number": 4,
                    "position": "Defender",
                    "photo": "https://media.api-sports.io/football/players/18776.png"
                },
                {
                    "id": 18936,
                    "name": "R. Bertrand",
                    "age": 33,
                    "number": 5,
                    "position": "Defender",
                    "photo": "https://media-1.api-sports.io/football/players/18936.png"
                },
                {
                    "id": 18772,
                    "name": "J. Evans",
                    "age": 34,
                    "number": 6,
                    "position": "Defender",
                    "photo": "https://media.api-sports.io/football/players/18772.png"
                },
                {
                    "id": 3421,
                    "name": "D. Amartey",
                    "age": 28,
                    "number": 18,
                    "position": "Defender",
                    "photo": "https://media.api-sports.io/football/players/3421.png"
                },
                {
                    "id": 18771,
                    "name": "Ricardo Pereira",
                    "age": 29,
                    "number": 21,
                    "position": "Defender",
                    "photo": "https://media.api-sports.io/football/players/18771.png"
                },
                {
                    "id": 18943,
                    "name": "J. Vestergaard",
                    "age": 30,
                    "number": 23,
                    "position": "Defender",
                    "photo": "https://media.api-sports.io/football/players/18943.png"
                },
                {
                    "id": 2920,
                    "name": "T. Castagne",
                    "age": 27,
                    "number": 27,
                    "position": "Defender",
                    "photo": "https://media-1.api-sports.io/football/players/2920.png"
                },
                {
                    "id": 152969,
                    "name": "L. Thomas",
                    "age": 21,
                    "number": 33,
                    "position": "Defender",
                    "photo": "https://media.api-sports.io/football/players/152969.png"
                },
                {
                    "id": 284396,
                    "name": "J. Wormleighton",
                    "age": 19,
                    "number": 60,
                    "position": "Defender",
                    "photo": "https://media-1.api-sports.io/football/players/284396.png"
                },
                {
                    "id": 18778,
                    "name": "H. Barnes",
                    "age": 25,
                    "number": 7,
                    "position": "Midfielder",
                    "photo": "https://media-1.api-sports.io/football/players/18778.png"
                },
                {
                    "id": 2926,
                    "name": "Y. Tielemans",
                    "age": 25,
                    "number": 8,
                    "position": "Midfielder",
                    "photo": "https://media-1.api-sports.io/football/players/2926.png"
                },
                {
                    "id": 18784,
                    "name": "J. Maddison",
                    "age": 26,
                    "number": 10,
                    "position": "Midfielder",
                    "photo": "https://media-1.api-sports.io/football/players/18784.png"
                },
                {
                    "id": 18777,
                    "name": "M. Albrighton",
                    "age": 33,
                    "number": 11,
                    "position": "Midfielder",
                    "photo": "https://media-1.api-sports.io/football/players/18777.png"
                },
                {
                    "id": 148099,
                    "name": "K. Dewsbury-Hall",
                    "age": 24,
                    "number": 22,
                    "position": "Midfielder",
                    "photo": "https://media.api-sports.io/football/players/148099.png"
                },
                {
                    "id": 18785,
                    "name": "N. Mendy",
                    "age": 30,
                    "number": 24,
                    "position": "Midfielder",
                    "photo": "https://media-1.api-sports.io/football/players/18785.png"
                },
                {
                    "id": 18786,
                    "name": "W. Ndidi",
                    "age": 26,
                    "number": 25,
                    "position": "Midfielder",
                    "photo": "https://media.api-sports.io/football/players/18786.png"
                },
                {
                    "id": 2925,
                    "name": "D. Praet",
                    "age": 28,
                    "number": 26,
                    "position": "Midfielder",
                    "photo": "https://media.api-sports.io/football/players/2925.png"
                },
                {
                    "id": 138929,
                    "name": "L. Brunt",
                    "age": 22,
                    "number": 34,
                    "position": "Midfielder",
                    "photo": "https://media-1.api-sports.io/football/players/138929.png"
                },
                {
                    "id": 22233,
                    "name": "B. Soumaré",
                    "age": 23,
                    "number": 42,
                    "position": "Midfielder",
                    "photo": "https://media-1.api-sports.io/football/players/22233.png"
                },
                {
                    "id": 289624,
                    "name": "S. Braybrooke",
                    "age": 18,
                    "number": 44,
                    "position": "Midfielder",
                    "photo": "https://media-1.api-sports.io/football/players/289624.png"
                },
                {
                    "id": 305733,
                    "name": "W. Alves",
                    "age": 17,
                    "number": null,
                    "position": "Midfielder",
                    "photo": "https://media-1.api-sports.io/football/players/305733.png"
                },
                {
                    "id": 283290,
                    "name": "K. McAteer",
                    "age": 21,
                    "number": null,
                    "position": "Midfielder",
                    "photo": "https://media-1.api-sports.io/football/players/283290.png"
                },
                {
                    "id": 18788,
                    "name": "J. Vardy",
                    "age": 35,
                    "number": 9,
                    "position": "Attacker",
                    "photo": "https://media-1.api-sports.io/football/players/18788.png"
                },
                {
                    "id": 2778,
                    "name": "K. Ịheanachọ",
                    "age": 26,
                    "number": 14,
                    "position": "Attacker",
                    "photo": "https://media-1.api-sports.io/football/players/2778.png"
                },
                {
                    "id": 18906,
                    "name": "Ayoze Pérez",
                    "age": 29,
                    "number": 17,
                    "position": "Attacker",
                    "photo": "https://media.api-sports.io/football/players/18906.png"
                },
                {
                    "id": 1098,
                    "name": "P. Daka",
                    "age": 24,
                    "number": 20,
                    "position": "Attacker",
                    "photo": "https://media.api-sports.io/football/players/1098.png"
                }
            ]
        }
    ]
}